odoo8_addon_partner_prospect-8.0.1.0.0.99.dev23-py2.7-nspkg.pth
odoo8_addon_partner_prospect-8.0.1.0.0.99.dev23.dist-info/METADATA
odoo8_addon_partner_prospect-8.0.1.0.0.99.dev23.dist-info/RECORD
odoo8_addon_partner_prospect-8.0.1.0.0.99.dev23.dist-info/WHEEL
odoo8_addon_partner_prospect-8.0.1.0.0.99.dev23.dist-info/namespace_packages.txt
odoo8_addon_partner_prospect-8.0.1.0.0.99.dev23.dist-info/top_level.txt
odoo_addons/partner_prospect/README.rst
odoo_addons/partner_prospect/__init__.py
odoo_addons/partner_prospect/__openerp__.py
odoo_addons/partner_prospect/i18n/am.po
odoo_addons/partner_prospect/i18n/ar.po
odoo_addons/partner_prospect/i18n/bg.po
odoo_addons/partner_prospect/i18n/bs.po
odoo_addons/partner_prospect/i18n/ca.po
odoo_addons/partner_prospect/i18n/cs.po
odoo_addons/partner_prospect/i18n/da.po
odoo_addons/partner_prospect/i18n/de.po
odoo_addons/partner_prospect/i18n/el_GR.po
odoo_addons/partner_prospect/i18n/en_GB.po
odoo_addons/partner_prospect/i18n/es.po
odoo_addons/partner_prospect/i18n/es_AR.po
odoo_addons/partner_prospect/i18n/es_CO.po
odoo_addons/partner_prospect/i18n/es_CR.po
odoo_addons/partner_prospect/i18n/es_EC.po
odoo_addons/partner_prospect/i18n/es_MX.po
odoo_addons/partner_prospect/i18n/es_PE.po
odoo_addons/partner_prospect/i18n/es_PY.po
odoo_addons/partner_prospect/i18n/es_VE.po
odoo_addons/partner_prospect/i18n/et.po
odoo_addons/partner_prospect/i18n/fa.po
odoo_addons/partner_prospect/i18n/fi.po
odoo_addons/partner_prospect/i18n/fr.po
odoo_addons/partner_prospect/i18n/fr_CH.po
odoo_addons/partner_prospect/i18n/gl.po
odoo_addons/partner_prospect/i18n/he.po
odoo_addons/partner_prospect/i18n/hr.po
odoo_addons/partner_prospect/i18n/hr_HR.po
odoo_addons/partner_prospect/i18n/hu.po
odoo_addons/partner_prospect/i18n/id.po
odoo_addons/partner_prospect/i18n/it.po
odoo_addons/partner_prospect/i18n/ja.po
odoo_addons/partner_prospect/i18n/ko.po
odoo_addons/partner_prospect/i18n/lt.po
odoo_addons/partner_prospect/i18n/lv.po
odoo_addons/partner_prospect/i18n/mk.po
odoo_addons/partner_prospect/i18n/mn.po
odoo_addons/partner_prospect/i18n/nb.po
odoo_addons/partner_prospect/i18n/nb_NO.po
odoo_addons/partner_prospect/i18n/nl.po
odoo_addons/partner_prospect/i18n/nl_BE.po
odoo_addons/partner_prospect/i18n/nl_NL.po
